{"schema":{"fields":[{"name":"index","type":"integer"},{"name":"open_price","type":"integer"},{"name":"high_price","type":"integer"},{"name":"low_price","type":"integer"},{"name":"close_price","type":"integer"},{"name":"code_id","type":"string"},{"name":"date","type":"string"},{"name":"volume","type":"integer"}],"primaryKey":["index"],"pandas_version":"0.20.0"},"data":[{"index":0,"open_price":6330,"high_price":6370,"low_price":6150,"close_price":6200,"code_id":"138490","date":"2019-02-28","volume":71584},{"index":1,"open_price":6320,"high_price":6340,"low_price":6230,"close_price":6310,"code_id":"138490","date":"2019-02-27","volume":24309},{"index":2,"open_price":6440,"high_price":6440,"low_price":6300,"close_price":6310,"code_id":"138490","date":"2019-02-26","volume":35132},{"index":3,"open_price":6360,"high_price":6450,"low_price":6350,"close_price":6400,"code_id":"138490","date":"2019-02-25","volume":30015},{"index":4,"open_price":6450,"high_price":6450,"low_price":6290,"close_price":6400,"code_id":"138490","date":"2019-02-22","volume":79317},{"index":5,"open_price":6530,"high_price":6530,"low_price":6370,"close_price":6440,"code_id":"138490","date":"2019-02-21","volume":39232},{"index":6,"open_price":6530,"high_price":6550,"low_price":6410,"close_price":6530,"code_id":"138490","date":"2019-02-20","volume":36624},{"index":7,"open_price":6570,"high_price":6570,"low_price":6460,"close_price":6510,"code_id":"138490","date":"2019-02-19","volume":22753},{"index":8,"open_price":6570,"high_price":6610,"low_price":6500,"close_price":6560,"code_id":"138490","date":"2019-02-18","volume":42594},{"index":9,"open_price":6580,"high_price":6620,"low_price":6530,"close_price":6580,"code_id":"138490","date":"2019-02-15","volume":33063},{"index":10,"open_price":6610,"high_price":6610,"low_price":6500,"close_price":6580,"code_id":"138490","date":"2019-02-14","volume":38130},{"index":11,"open_price":6540,"high_price":6580,"low_price":6430,"close_price":6560,"code_id":"138490","date":"2019-02-13","volume":59538},{"index":12,"open_price":6550,"high_price":6590,"low_price":6430,"close_price":6500,"code_id":"138490","date":"2019-02-12","volume":39929},{"index":13,"open_price":6480,"high_price":6550,"low_price":6430,"close_price":6550,"code_id":"138490","date":"2019-02-11","volume":55653},{"index":14,"open_price":6490,"high_price":6540,"low_price":6370,"close_price":6540,"code_id":"138490","date":"2019-02-08","volume":39493},{"index":15,"open_price":6460,"high_price":6510,"low_price":6360,"close_price":6490,"code_id":"138490","date":"2019-02-07","volume":36416},{"index":16,"open_price":6310,"high_price":6450,"low_price":6310,"close_price":6440,"code_id":"138490","date":"2019-02-01","volume":24988},{"index":17,"open_price":6320,"high_price":6460,"low_price":6290,"close_price":6370,"code_id":"138490","date":"2019-01-31","volume":94689},{"index":18,"open_price":6350,"high_price":6500,"low_price":6300,"close_price":6350,"code_id":"138490","date":"2019-01-30","volume":60492},{"index":19,"open_price":6460,"high_price":6490,"low_price":6280,"close_price":6340,"code_id":"138490","date":"2019-01-29","volume":53100},{"index":20,"open_price":6500,"high_price":6540,"low_price":6430,"close_price":6510,"code_id":"138490","date":"2019-01-28","volume":53028},{"index":21,"open_price":6540,"high_price":6580,"low_price":6460,"close_price":6520,"code_id":"138490","date":"2019-01-25","volume":27382},{"index":22,"open_price":6600,"high_price":6600,"low_price":6500,"close_price":6540,"code_id":"138490","date":"2019-01-24","volume":46558},{"index":23,"open_price":6470,"high_price":6620,"low_price":6460,"close_price":6600,"code_id":"138490","date":"2019-01-23","volume":42986},{"index":24,"open_price":6770,"high_price":6780,"low_price":6470,"close_price":6540,"code_id":"138490","date":"2019-01-22","volume":156615},{"index":25,"open_price":6160,"high_price":6700,"low_price":6060,"close_price":6680,"code_id":"138490","date":"2019-01-21","volume":427247},{"index":26,"open_price":5990,"high_price":6100,"low_price":5980,"close_price":6060,"code_id":"138490","date":"2019-01-18","volume":37114},{"index":27,"open_price":6070,"high_price":6110,"low_price":6010,"close_price":6040,"code_id":"138490","date":"2019-01-17","volume":25019},{"index":28,"open_price":6050,"high_price":6100,"low_price":6010,"close_price":6100,"code_id":"138490","date":"2019-01-16","volume":37830},{"index":29,"open_price":6070,"high_price":6080,"low_price":5950,"close_price":6050,"code_id":"138490","date":"2019-01-15","volume":24874},{"index":30,"open_price":5920,"high_price":6050,"low_price":5920,"close_price":6040,"code_id":"138490","date":"2019-01-14","volume":73176},{"index":31,"open_price":5740,"high_price":5930,"low_price":5730,"close_price":5920,"code_id":"138490","date":"2019-01-11","volume":25949},{"index":32,"open_price":5910,"high_price":5960,"low_price":5670,"close_price":5790,"code_id":"138490","date":"2019-01-10","volume":79071},{"index":33,"open_price":5800,"high_price":5960,"low_price":5800,"close_price":5910,"code_id":"138490","date":"2019-01-09","volume":31807},{"index":34,"open_price":5850,"high_price":5950,"low_price":5840,"close_price":5850,"code_id":"138490","date":"2019-01-08","volume":16526},{"index":35,"open_price":5800,"high_price":5910,"low_price":5750,"close_price":5910,"code_id":"138490","date":"2019-01-07","volume":42706},{"index":36,"open_price":5690,"high_price":5790,"low_price":5670,"close_price":5750,"code_id":"138490","date":"2019-01-04","volume":19437},{"index":37,"open_price":5800,"high_price":5800,"low_price":5710,"close_price":5720,"code_id":"138490","date":"2019-01-03","volume":53953},{"index":38,"open_price":5650,"high_price":5830,"low_price":5650,"close_price":5700,"code_id":"138490","date":"2019-01-02","volume":42602}]}