{"schema":{"fields":[{"name":"index","type":"integer"},{"name":"open_price","type":"integer"},{"name":"high_price","type":"integer"},{"name":"low_price","type":"integer"},{"name":"close_price","type":"integer"},{"name":"code_id","type":"string"},{"name":"date","type":"string"},{"name":"volume","type":"integer"}],"primaryKey":["index"],"pandas_version":"0.20.0"},"data":[{"index":0,"open_price":138500,"high_price":149000,"low_price":135500,"close_price":141500,"code_id":"192400","date":"2019-02-28","volume":19058},{"index":1,"open_price":141000,"high_price":141000,"low_price":135000,"close_price":138000,"code_id":"192400","date":"2019-02-27","volume":15956},{"index":2,"open_price":139500,"high_price":142000,"low_price":136500,"close_price":141500,"code_id":"192400","date":"2019-02-26","volume":9622},{"index":3,"open_price":140000,"high_price":142500,"low_price":133500,"close_price":141500,"code_id":"192400","date":"2019-02-25","volume":9969},{"index":4,"open_price":141500,"high_price":142000,"low_price":137000,"close_price":137000,"code_id":"192400","date":"2019-02-22","volume":3671},{"index":5,"open_price":138500,"high_price":145000,"low_price":137500,"close_price":140000,"code_id":"192400","date":"2019-02-21","volume":5361},{"index":6,"open_price":139000,"high_price":142000,"low_price":137000,"close_price":139000,"code_id":"192400","date":"2019-02-20","volume":3755},{"index":7,"open_price":135500,"high_price":138500,"low_price":133500,"close_price":138500,"code_id":"192400","date":"2019-02-19","volume":5215},{"index":8,"open_price":137500,"high_price":139500,"low_price":136000,"close_price":136500,"code_id":"192400","date":"2019-02-18","volume":3590},{"index":9,"open_price":135000,"high_price":141000,"low_price":135000,"close_price":138500,"code_id":"192400","date":"2019-02-15","volume":4119},{"index":10,"open_price":135000,"high_price":139000,"low_price":134000,"close_price":137500,"code_id":"192400","date":"2019-02-14","volume":6621},{"index":11,"open_price":126000,"high_price":137500,"low_price":125500,"close_price":136000,"code_id":"192400","date":"2019-02-13","volume":17050},{"index":12,"open_price":123500,"high_price":127500,"low_price":123500,"close_price":125000,"code_id":"192400","date":"2019-02-12","volume":3775},{"index":13,"open_price":124000,"high_price":125000,"low_price":122500,"close_price":124000,"code_id":"192400","date":"2019-02-11","volume":8434},{"index":14,"open_price":123000,"high_price":124500,"low_price":121500,"close_price":123000,"code_id":"192400","date":"2019-02-08","volume":6067},{"index":15,"open_price":126000,"high_price":126000,"low_price":122000,"close_price":123000,"code_id":"192400","date":"2019-02-07","volume":7036},{"index":16,"open_price":125000,"high_price":127000,"low_price":124000,"close_price":124500,"code_id":"192400","date":"2019-02-01","volume":6743},{"index":17,"open_price":129500,"high_price":129500,"low_price":123000,"close_price":125000,"code_id":"192400","date":"2019-01-31","volume":8117},{"index":18,"open_price":127000,"high_price":129000,"low_price":126500,"close_price":127000,"code_id":"192400","date":"2019-01-30","volume":4082},{"index":19,"open_price":126000,"high_price":129500,"low_price":125000,"close_price":127000,"code_id":"192400","date":"2019-01-29","volume":7020},{"index":20,"open_price":132000,"high_price":132000,"low_price":125000,"close_price":126500,"code_id":"192400","date":"2019-01-28","volume":5199},{"index":21,"open_price":126500,"high_price":131000,"low_price":124500,"close_price":129000,"code_id":"192400","date":"2019-01-25","volume":6022},{"index":22,"open_price":127000,"high_price":129000,"low_price":126000,"close_price":126500,"code_id":"192400","date":"2019-01-24","volume":2908},{"index":23,"open_price":123500,"high_price":130000,"low_price":122500,"close_price":129000,"code_id":"192400","date":"2019-01-23","volume":5141},{"index":24,"open_price":123500,"high_price":125000,"low_price":122000,"close_price":122500,"code_id":"192400","date":"2019-01-22","volume":2423},{"index":25,"open_price":124500,"high_price":124500,"low_price":122000,"close_price":124000,"code_id":"192400","date":"2019-01-21","volume":3254},{"index":26,"open_price":123000,"high_price":124000,"low_price":123000,"close_price":123000,"code_id":"192400","date":"2019-01-18","volume":1811},{"index":27,"open_price":125000,"high_price":125500,"low_price":121000,"close_price":122000,"code_id":"192400","date":"2019-01-17","volume":4592},{"index":28,"open_price":129000,"high_price":130000,"low_price":123000,"close_price":123500,"code_id":"192400","date":"2019-01-16","volume":5317},{"index":29,"open_price":130000,"high_price":134000,"low_price":128000,"close_price":128000,"code_id":"192400","date":"2019-01-15","volume":6922},{"index":30,"open_price":131000,"high_price":134000,"low_price":128500,"close_price":129000,"code_id":"192400","date":"2019-01-14","volume":4431},{"index":31,"open_price":124000,"high_price":133000,"low_price":123500,"close_price":130000,"code_id":"192400","date":"2019-01-11","volume":12272},{"index":32,"open_price":128000,"high_price":130500,"low_price":122000,"close_price":123500,"code_id":"192400","date":"2019-01-10","volume":5497},{"index":33,"open_price":122500,"high_price":130000,"low_price":121500,"close_price":129000,"code_id":"192400","date":"2019-01-09","volume":8207},{"index":34,"open_price":123000,"high_price":124500,"low_price":121500,"close_price":123000,"code_id":"192400","date":"2019-01-08","volume":5708},{"index":35,"open_price":124000,"high_price":124000,"low_price":120500,"close_price":123000,"code_id":"192400","date":"2019-01-07","volume":6213},{"index":36,"open_price":115000,"high_price":124000,"low_price":115000,"close_price":122000,"code_id":"192400","date":"2019-01-04","volume":9522},{"index":37,"open_price":118000,"high_price":119500,"low_price":114000,"close_price":116500,"code_id":"192400","date":"2019-01-03","volume":4570},{"index":38,"open_price":119500,"high_price":121000,"low_price":117000,"close_price":118000,"code_id":"192400","date":"2019-01-02","volume":4363}]}